glotaran/__init__.py
glotaran/analysis/__init__.py
glotaran/analysis/matrix_calculation.py
glotaran/analysis/nnls.py
glotaran/analysis/optimize.py
glotaran/analysis/problem_bag.py
glotaran/analysis/residual_calculation.py
glotaran/analysis/result.py
glotaran/analysis/scheme.py
glotaran/analysis/simulation.py
glotaran/analysis/variable_projection.py
glotaran/analysis/test/__init__.py
glotaran/analysis/test/mock.py
glotaran/analysis/test/test_grouping.py
glotaran/analysis/test/test_optimization.py
glotaran/analysis/test/test_scheme.py
glotaran/analysis/test/test_simulation.py
glotaran/builtin/__init__.py
glotaran/builtin/file_formats/__init__.py
glotaran/builtin/file_formats/ascii/__init__.py
glotaran/builtin/file_formats/ascii/wavelength_time_explicit_file.py
glotaran/builtin/file_formats/sdt/__init__.py
glotaran/builtin/file_formats/sdt/sdt_file.py
glotaran/builtin/file_formats/sdt/sdt_file_reader.py
glotaran/builtin/file_formats/sdt/test/__init__.py
glotaran/builtin/file_formats/sdt/test/test_file_readers.py
glotaran/builtin/models/__init__.py
glotaran/builtin/models/doas/__init__.py
glotaran/builtin/models/doas/doas_matrix.py
glotaran/builtin/models/doas/doas_megacomplex.py
glotaran/builtin/models/doas/doas_model.py
glotaran/builtin/models/doas/doas_result.py
glotaran/builtin/models/doas/doas_spectral_matrix.py
glotaran/builtin/models/doas/oscillation.py
glotaran/builtin/models/kinetic_image/__init__.py
glotaran/builtin/models/kinetic_image/initial_concentration.py
glotaran/builtin/models/kinetic_image/irf.py
glotaran/builtin/models/kinetic_image/k_matrix.py
glotaran/builtin/models/kinetic_image/kinetic_image_dataset_descriptor.py
glotaran/builtin/models/kinetic_image/kinetic_image_matrix.py
glotaran/builtin/models/kinetic_image/kinetic_image_megacomplex.py
glotaran/builtin/models/kinetic_image/kinetic_image_model.py
glotaran/builtin/models/kinetic_image/kinetic_image_result.py
glotaran/builtin/models/kinetic_image/test/__init__.py
glotaran-0.1.0.dist-info/AUTHORS.rst
glotaran-0.1.0.dist-info/LICENSE
glotaran-0.1.0.dist-info/METADATA
glotaran-0.1.0.dist-info/WHEEL
glotaran-0.1.0.dist-info/entry_points.txt
glotaran-0.1.0.dist-info/top_level.txt
glotaran-0.1.0.dist-info/zip-safe
glotaran-0.1.0.dist-info/RECORD
