Metadata-Version: 2.1
Name: glotaran
Version: 0.1.0
Summary: The Glotaran fitting engine.
Home-page: https://github.com/glotaran/pyglotaran
Author: Joern Weissenborn, Joris Snellenburg, Ivo van Stokkum
Author-email: joern.weissenborn@gmail.com,
License: GPLv3
Project-URL: GloTarAn Ecosystem, http://glotaran.org
Project-URL: Documentation, https://glotaran.readthedocs.io
Project-URL: Source, https://github.com/glotaran/pyglotaran
Project-URL: Tracker, https://github.com/glotaran/pyglotaran/issues
Platform: UNKNOWN
Classifier: Development Status :: 2 - Pre-Alpha
Classifier: Intended Audience :: Science/Research
Classifier: License :: OSI Approved :: GNU General Public License v3 (GPLv3)
Classifier: Operating System :: OS Independent
Classifier: Natural Language :: English
Classifier: Programming Language :: Python :: 3
Classifier: Programming Language :: Python :: 3.6
Classifier: Programming Language :: Python :: 3.7
Classifier: Programming Language :: Python :: 3.8
Classifier: Topic :: Scientific/Engineering
Classifier: Topic :: Scientific/Engineering :: Physics
Classifier: Topic :: Scientific/Engineering :: Chemistry
Requires-Python: >=3.6, <3.9
Requires-Dist: click (>=7.0)
Requires-Dist: cloudpickle (>=1.2)
Requires-Dist: dask[bag] (>=2.8)
Requires-Dist: lmfit (>=0.9.13)
Requires-Dist: netCDF4 (>=1.5.3)
Requires-Dist: numba (>=0.48)
Requires-Dist: numpy (>=1.17.3)
Requires-Dist: pandas (>=0.25.2)
Requires-Dist: pyyaml (>=5.2)
Requires-Dist: scipy (>=1.3.2)
Requires-Dist: setuptools (>=41.2)
Requires-Dist: xarray (>=0.14)
